stdlogging.py
test.py
stdlogging-0.15.dist-info/DESCRIPTION.rst
stdlogging-0.15.dist-info/METADATA
stdlogging-0.15.dist-info/RECORD
stdlogging-0.15.dist-info/WHEEL
stdlogging-0.15.dist-info/metadata.json
stdlogging-0.15.dist-info/top_level.txt
