Metadata-Version: 2.0
Name: stdlogging
Version: 0.15
Summary: Capture stdout and stderr output by logging
Home-page: https://github.com/fx-kirin/py-stdlogging
Author: fx-kirin
Author-email: ono.kirin@gmail.com
License: UNKNOWN
Platform: UNKNOWN
